fpefs/__init__.py
fpefs/fpefs.py
fpefs-0.1.dist-info/LICENSE
fpefs-0.1.dist-info/METADATA
fpefs-0.1.dist-info/WHEEL
fpefs-0.1.dist-info/top_level.txt
fpefs-0.1.dist-info/RECORD
